mkdocs_bootstrap4/__init__.py
mkdocs_bootstrap4/base.html
mkdocs_bootstrap4/content.html
mkdocs_bootstrap4/keyboard-modal.html
mkdocs_bootstrap4/main.html
mkdocs_bootstrap4/mkdocs_theme.yml
mkdocs_bootstrap4/nav-sub.html
mkdocs_bootstrap4/search-modal.html
mkdocs_bootstrap4/toc.html
mkdocs_bootstrap4/css/base.css
mkdocs_bootstrap4/css/bootstrap-3.3.7.min.css
mkdocs_bootstrap4/css/bootstrap.min.css
mkdocs_bootstrap4/css/font-awesome.min.css
mkdocs_bootstrap4/fonts/fontawesome-webfont.eot
mkdocs_bootstrap4/fonts/fontawesome-webfont.svg
mkdocs_bootstrap4/fonts/fontawesome-webfont.ttf
mkdocs_bootstrap4/fonts/fontawesome-webfont.woff
mkdocs_bootstrap4/js/base.js
mkdocs_bootstrap4/js/bootstrap-3.3.7.min.js
mkdocs_bootstrap4/js/bootstrap.min.js
mkdocs_bootstrap4/js/jquery.min.js
mkdocs_bootstrap4-0.1.5.dist-info/LICENSE
mkdocs_bootstrap4-0.1.5.dist-info/METADATA
mkdocs_bootstrap4-0.1.5.dist-info/WHEEL
mkdocs_bootstrap4-0.1.5.dist-info/entry_points.txt
mkdocs_bootstrap4-0.1.5.dist-info/top_level.txt
mkdocs_bootstrap4-0.1.5.dist-info/RECORD
