Metadata-Version: 2.1
Name: mkdocs-bootstrap4
Version: 0.1.5
Summary: Bootstrap4 theme for MkDocs
Home-page: https://github.com/byrnereese/mkdocs-bootstrap4/
Author: Byrne Reese
Author-email: byrne@majordojo.com
License: MIT
Platform: UNKNOWN
Requires-Python: >=2.7.9,!=3.0.*,!=3.1.*,!=3.2.*,!=3.3.*
Requires-Dist: mkdocs (>=1.1)
Requires-Dist: mkdocs-git-committers-plugin (>=0.2.0)
